[{"event": "charging_started", "time": 1770014160.0, "bus_vin": "VIN-1401", "bus_number": 1401, "location_id": "Norfolk", "charger_id": "HVC29", "connector_id": "HVC29-1", "soc_percent": 43.197278911564624, "target_soc": 85.0, "strategy_name": "SOC_THRESHOLD", "power_kw": 0.0, "location_total_power_kw": 0.0}, {"event": "charging_progress", "time": 1770014460.0, "bus_vin": "VIN-1401", "bus_number": 1401, "location_id": "Norfolk", "charger_id": "HVC29", "connector_id": "HVC29-1", "soc_percent": 49.47790529666137, "power_kw": 265.89659863945576, "location_total_power_kw": 265.89659863945576, "strategy_name": "SOC_THRESHOLD"}, {"event": "charging_progress", "time": 1770014760.0, "bus_vin": "VIN-1401", "bus_number": 1401, "location_id": "Norfolk", "charger_id": "HVC29", "connector_id": "HVC29-1", "soc_percent": 55.81312518397172, "power_kw": 268.20786914917136, "location_total_power_kw": 268.20786914917136, "strategy_name": "SOC_THRESHOLD"}, {"event": "charging_progress", "time": 1770015060.0, "bus_vin": "VIN-1401", "bus_number": 1401, "location_id": "Norfolk", "charger_id": "HVC29", "connector_id": "HVC29-1", "soc_percent": 62.20341312018917, "power_kw": 270.53923006770157, "location_total_power_kw": 270.53923006770157, "strategy_name": "SOC_THRESHOLD"}, {"event": "charging_progress", "time": 1770015360.0, "bus_vin": "VIN-1401", "bus_number": 1401, "location_id": "Norfolk", "charger_id": "HVC29", "connector_id": "HVC29-1", "soc_percent": 68.64924777694063, "power_kw": 272.8908560282296, "location_total_power_kw": 272.8908560282296, "strategy_name": "SOC_THRESHOLD"}, {"event": "charging_progress", "time": 1770015660.0, "bus_vin": "VIN-1401", "bus_number": 1401, "location_id": "Norfolk", "charger_id": "HVC29", "connector_id": "HVC29-1", "soc_percent": 75.15111198664192, "power_kw": 275.2629231819142, "location_total_power_kw": 275.2629231819142, "strategy_name": "SOC_THRESHOLD"}, {"event": "charging_progress", "time": 1770015960.0, "bus_vin": "VIN-1401", "bus_number": 1401, "location_id": "Norfolk", "charger_id": "HVC29", "connector_id": "HVC29-1", "soc_percent": 81.70949277866488, "power_kw": 277.6556092110842, "location_total_power_kw": 277.6556092110842, "strategy_name": "SOC_THRESHOLD"}, {"event": "charging_progress", "time": 1770016260.0, "bus_vin": "VIN-1401", "bus_number": 1401, "location_id": "Norfolk", "charger_id": "HVC29", "connector_id": "HVC29-1", "soc_percent": 88.3248814158188, "power_kw": 280.0690933425487, "location_total_power_kw": 280.0690933425487, "strategy_name": "SOC_THRESHOLD"}, {"event": "charging_stopped", "time": 1770016260.0, "bus_vin": "VIN-1401", "bus_number": 1401, "location_id": "Norfolk", "charger_id": "HVC29", "connector_id": "HVC29-1", "soc_percent": 88.3248814158188}, {"event": "charging_started", "time": 1770021360.0, "bus_vin": "VIN-1402", "bus_number": 1402, "location_id": "Kijkduin", "charger_id": "HVC31", "connector_id": "HVC31-1", "soc_percent": 48.19727891156464, "target_soc": 85.0, "strategy_name": "SOC_THRESHOLD", "power_kw": 0.0, "location_total_power_kw": 0.0}, {"event": "charging_progress", "time": 1770021660.0, "bus_vin": "VIN-1402", "bus_number": 1402, "location_id": "Kijkduin", "charger_id": "HVC31", "connector_id": "HVC31-1", "soc_percent": 54.52136712583749, "power_kw": 267.7365986394558, "location_total_power_kw": 267.7365986394558, "strategy_name": "SOC_THRESHOLD"}, {"event": "charging_progress", "time": 1770021960.0, "bus_vin": "VIN-1402", "bus_number": 1402, "location_id": "Kijkduin", "charger_id": "HVC31", "connector_id": "HVC31-1", "soc_percent": 60.900426628443036, "power_kw": 270.0638631023082, "location_total_power_kw": 270.0638631023082, "strategy_name": "SOC_THRESHOLD"}, {"event": "charging_progress", "time": 1770022260.0, "bus_vin": "VIN-1402", "bus_number": 1402, "location_id": "Kijkduin", "charger_id": "HVC31", "connector_id": "HVC31-1", "soc_percent": 67.33493524992988, "power_kw": 272.411356999267, "location_total_power_kw": 272.411356999267, "strategy_name": "SOC_THRESHOLD"}, {"event": "charging_progress", "time": 1770022560.0, "bus_vin": "VIN-1402", "bus_number": 1402, "location_id": "Kijkduin", "charger_id": "HVC31", "connector_id": "HVC31-1", "soc_percent": 73.82537497432459, "power_kw": 274.7792561719742, "location_total_power_kw": 274.7792561719742, "strategy_name": "SOC_THRESHOLD"}, {"event": "charging_progress", "time": 1770022860.0, "bus_vin": "VIN-1402", "bus_number": 1402, "location_id": "Kijkduin", "charger_id": "HVC31", "connector_id": "HVC31-1", "soc_percent": 80.3722319752352, "power_kw": 277.1677379905515, "location_total_power_kw": 277.1677379905515, "strategy_name": "SOC_THRESHOLD"}, {"event": "charging_progress", "time": 1770023160.0, "bus_vin": "VIN-1402", "bus_number": 1402, "location_id": "Kijkduin", "charger_id": "HVC31", "connector_id": "HVC31-1", "soc_percent": 86.9759966522686, "power_kw": 279.57698136688657, "location_total_power_kw": 279.57698136688657, "strategy_name": "SOC_THRESHOLD"}, {"event": "charging_stopped", "time": 1770023160.0, "bus_vin": "VIN-1402", "bus_number": 1402, "location_id": "Kijkduin", "charger_id": "HVC31", "connector_id": "HVC31-1", "soc_percent": 86.9759966522686}, {"event": "charging_started", "time": 1770028560.0, "bus_vin": "VIN-1403", "bus_number": 1403, "location_id": "Zwarte Pad", "charger_id": "HVC37", "connector_id": "HVC37-1", "soc_percent": 53.19727891156464, "target_soc": 85.0, "strategy_name": "SOC_THRESHOLD", "power_kw": 0.0, "location_total_power_kw": 0.0}, {"event": "charging_progress", "time": 1770028860.0, "bus_vin": "VIN-1403", "bus_number": 1403, "location_id": "Zwarte Pad", "charger_id": "HVC37", "connector_id": "HVC37-1", "soc_percent": 59.56482895501362, "power_kw": 269.57659863945577, "location_total_power_kw": 269.57659863945577, "strategy_name": "SOC_THRESHOLD"}, {"event": "charging_progress", "time": 1770029160.0, "bus_vin": "VIN-1403", "bus_number": 1403, "location_id": "Zwarte Pad", "charger_id": "HVC37", "connector_id": "HVC37-1", "soc_percent": 65.98772807291434, "power_kw": 271.919857055445, "location_total_power_kw": 271.919857055445, "strategy_name": "SOC_THRESHOLD"}, {"event": "charging_progress", "time": 1770029460.0, "bus_vin": "VIN-1403", "bus_number": 1403, "location_id": "Zwarte Pad", "charger_id": "HVC37", "connector_id": "HVC37-1", "soc_percent": 72.46645737967057, "power_kw": 274.28348393083246, "location_total_power_kw": 274.28348393083246, "strategy_name": "SOC_THRESHOLD"}, {"event": "charging_progress", "time": 1770029760.0, "bus_vin": "VIN-1403", "bus_number": 1403, "location_id": "Zwarte Pad", "charger_id": "HVC37", "connector_id": "HVC37-1", "soc_percent": 79.00150217170851, "power_kw": 276.6676563157188, "location_total_power_kw": 276.6676563157188, "strategy_name": "SOC_THRESHOLD"}, {"event": "charging_progress", "time": 1770030060.0, "bus_vin": "VIN-1403", "bus_number": 1403, "location_id": "Zwarte Pad", "charger_id": "HVC37", "connector_id": "HVC37-1", "soc_percent": 85.59335196382843, "power_kw": 279.0725527991887, "location_total_power_kw": 279.0725527991887, "strategy_name": "SOC_THRESHOLD"}, {"event": "charging_stopped", "time": 1770030060.0, "bus_vin": "VIN-1403", "bus_number": 1403, "location_id": "Zwarte Pad", "charger_id": "HVC37", "connector_id": "HVC37-1", "soc_percent": 85.59335196382843}]